Auto_diff/__init__.py
Auto_diff/fd/FD.py
Auto_diff/fd/__init__.py
Auto_diff/rd/RD.py
Auto_diff/rd/__init__.py
Auto_diff/tests/__init__.py
Auto_diff/tests/test_basic_v2.py
Auto_diff/tests/test_jacobian.py
Auto_diff/tests/test_rd.py
Auto_diff/utils/__init__.py
Auto_diff/utils/jacobian.py
iamautodiff-0.0.2.dist-info/LICENSE
iamautodiff-0.0.2.dist-info/METADATA
iamautodiff-0.0.2.dist-info/WHEEL
iamautodiff-0.0.2.dist-info/top_level.txt
iamautodiff-0.0.2.dist-info/RECORD
