Metadata-Version: 2.1
Name: iamautodiff
Version: 0.0.2
Summary: A package for forward and reverse automatic differentiation
Home-page: https://github.com/AutoDiff-Dream-Team/cs107-FinalProject
Author: AC 207 Group 24 (Diego | Nishu | Victor | Yuxin)
Author-email: nlahoti@mde.harvard.edu
License: UNKNOWN
Platform: UNKNOWN
Classifier: Programming Language :: Python :: 3
Classifier: License :: OSI Approved :: MIT License
Classifier: Operating System :: OS Independent
Requires-Python: >=3.6
